{
    "version": 1,
    "license": "CC-BY-SA-3.0",
    "copyright": "By Starlighthowls for Impstation",
    "MetaAtlas": false,
    "size": {
      "x": 32,
      "y": 32
    },
    "states": [
      {
        "name": "icon",
        "delays": [
          [
            1,
            1
          ]
        ]
      },
      {
        "name": "lawvendglow",
        "delays": [
          [
            1,
            1
          ]
        ]
      },
      {
       "name": "lawvendbase"
      }
    ]
  }
